donnes_des_sous_mathis/__init__.py
donnes_des_sous_mathis/banque.py
donnes_des_sous_mathis-0.1.1.dist-info/WHEEL
donnes_des_sous_mathis-0.1.1.dist-info/entry_points.txt
donnes_des_sous_mathis-0.1.1.dist-info/METADATA
donnes_des_sous_mathis-0.1.1.dist-info/RECORD
