Metadata-Version: 2.3
Name: donnes-des-sous-mathis
Version: 0.1.1
Summary: Add your description here
Author: Mathis
Author-email: Mathis <mathis.rade@gmail.com>
Requires-Dist: httpx==0.28.1
Requires-Python: >=3.11
